fakemoneyd/__init__.py
fakemoneyd/admin.py
fakemoneyd/apps.py
fakemoneyd/models.py
fakemoneyd/tests.py
fakemoneyd/urls.py
fakemoneyd/views.py
fakemoneyd/management/__init__.py
fakemoneyd/management/commands/__init__.py
fakemoneyd/management/commands/seed_currencies.py
fakemoneyd/migrations/0001_initial.py
fakemoneyd/migrations/0002_currency_meta_ordering.py
fakemoneyd/migrations/0003_demofakemoneymodelbase.py
fakemoneyd/migrations/__init__.py
django_fakemoneyd-0.1.1.dist-info/LICENSE
django_fakemoneyd-0.1.1.dist-info/METADATA
django_fakemoneyd-0.1.1.dist-info/WHEEL
django_fakemoneyd-0.1.1.dist-info/top_level.txt
django_fakemoneyd-0.1.1.dist-info/RECORD
